Metadata-Version: 2.1
Name: schemainspect
Version: 3.1.1652015119
Summary: Schema inspection for PostgreSQL (and possibly others)
Home-page: https://github.com/djrobstep/schemainspect
License: Unlicense
Author: Robert Lechte
Author-email: robertlechte@gmail.com
Requires-Python: >=3.7,<4
Classifier: License :: Other/Proprietary License
Classifier: Programming Language :: Python :: 3
Classifier: Programming Language :: Python :: 3.10
Classifier: Programming Language :: Python :: 3.7
Classifier: Programming Language :: Python :: 3.8
Classifier: Programming Language :: Python :: 3.9
Requires-Dist: sqlalchemy
Project-URL: Repository, https://github.com/djrobstep/schemainspect
